odoo/addons/connector_prestashop_environment/README.rst
odoo/addons/connector_prestashop_environment/__init__.py
odoo/addons/connector_prestashop_environment/__manifest__.py
odoo/addons/connector_prestashop_environment/i18n/connector_prestashop_environment.pot
odoo/addons/connector_prestashop_environment/i18n/es.po
odoo/addons/connector_prestashop_environment/i18n/it.po
odoo/addons/connector_prestashop_environment/models/__init__.py
odoo/addons/connector_prestashop_environment/models/prestashop_backend.py
odoo/addons/connector_prestashop_environment/readme/CONTRIBUTORS.rst
odoo/addons/connector_prestashop_environment/readme/DESCRIPTION.rst
odoo/addons/connector_prestashop_environment/static/description/icon.png
odoo/addons/connector_prestashop_environment/static/description/index.html
odoo14_addon_connector_prestashop_environment-14.0.1.0.1.dev10.dist-info/METADATA
odoo14_addon_connector_prestashop_environment-14.0.1.0.1.dev10.dist-info/WHEEL
odoo14_addon_connector_prestashop_environment-14.0.1.0.1.dev10.dist-info/top_level.txt
odoo14_addon_connector_prestashop_environment-14.0.1.0.1.dev10.dist-info/RECORD
